odoo/addons/portal_pos_order_amount/README.rst
odoo/addons/portal_pos_order_amount/__init__.py
odoo/addons/portal_pos_order_amount/__manifest__.py
odoo/addons/portal_pos_order_amount/controllers/__init__.py
odoo/addons/portal_pos_order_amount/controllers/main.py
odoo/addons/portal_pos_order_amount/i18n/fr.po
odoo/addons/portal_pos_order_amount/i18n/portal_pos_order_amount.pot
odoo/addons/portal_pos_order_amount/readme/CONTRIBUTORS.rst
odoo/addons/portal_pos_order_amount/readme/DESCRIPTION.rst
odoo/addons/portal_pos_order_amount/readme/ROADMAP.rst
odoo/addons/portal_pos_order_amount/static/description/index.html
odoo/addons/portal_pos_order_amount/templates/portal_pos_order_amount.xml
odoo_addon_portal_pos_order_amount-16.0.1.0.0.5.dist-info/METADATA
odoo_addon_portal_pos_order_amount-16.0.1.0.0.5.dist-info/WHEEL
odoo_addon_portal_pos_order_amount-16.0.1.0.0.5.dist-info/top_level.txt
odoo_addon_portal_pos_order_amount-16.0.1.0.0.5.dist-info/RECORD
