Metadata-Version: 2.1
Name: odoo-addon-portal_pos_order_amount
Version: 16.0.1.0.0.5
Requires-Python: >=3.10
Requires-Dist: odoo>=16.0a,<16.1dev
Summary: Show the total amount of pos order in the website portal.
Home-page: https://github.com/beescoop/Obeesdoo
License: AGPL-3
Author: Coop IT Easy SC
Classifier: Programming Language :: Python
Classifier: Framework :: Odoo
Classifier: Framework :: Odoo :: 16.0
Classifier: License :: OSI Approved :: GNU Affero General Public License v3
